MANIFEST.in
README.rst
setup.cfg
setup.py
webbed/__init__.py
webbed/__main__.py
webbed/main.py
webbed/version.py
webbed.egg-info/PKG-INFO
webbed.egg-info/SOURCES.txt
webbed.egg-info/dependency_links.txt
webbed.egg-info/top_level.txt