Metadata-Version: 1.1
Name: webbed
Version: 0.0.2
Summary: Allows the execution of python code within any file
Home-page: https://github.com/Zaeb0s/webbed
Author: Christoffer Zakrisson
Author-email: christoffer_zakrisson@hotmail.com
License: MIT
Keywords: webbed,script,file
Platform: UNKNOWN
Classifier: Development Status :: 4 - Beta
Classifier: Programming Language :: Python :: 3.5
Classifier: Operating System :: POSIX :: Linux
Classifier: Operating System :: POSIX :: Linux
Classifier: License :: OSI Approved :: MIT License
